celus_pycounter/__init__.py
celus_pycounter/constants.py
celus_pycounter/csvhelper.py
celus_pycounter/exceptions.py
celus_pycounter/helpers.py
celus_pycounter/report.py
celus_pycounter/schemas/counter4_1.xsd
celus_pycounter/schemas/counterElements4_1.xsd
celus_pycounter/schemas/counter_sushi4_1.xsd
celus_pycounter/schemas/soap.xsd
celus_pycounter/schemas/sushi1_6.xsd
celus_pycounter/sushi.py
celus_pycounter/sushi5.py
celus_pycounter/sushiclient.py
celus_pycounter/version.py
celus_pycounter-5.0.0.dist-info/LICENSE.txt
celus_pycounter-5.0.0.dist-info/METADATA
celus_pycounter-5.0.0.dist-info/WHEEL
celus_pycounter-5.0.0.dist-info/entry_points.txt
celus_pycounter-5.0.0.dist-info/RECORD
