Metadata-Version: 2.1
Name: celus-pycounter
Version: 5.0.0
Summary: Project COUNTER/NISO SUSHI statistics
License: MIT
Keywords: COUNTER,SUSHI
Author: Geoffrey Spear
Author-email: speargh@pitt.edu
Requires-Python: >=3.12,<4.0
Classifier: Intended Audience :: Developers
Classifier: License :: OSI Approved :: MIT License
Classifier: Programming Language :: Python :: 3
Classifier: Programming Language :: Python :: 3.12
Classifier: Programming Language :: Python :: 3.13
Classifier: Topic :: Software Development :: Libraries
Requires-Dist: click (>=8.3.0,<8.4.0)
Requires-Dist: lxml (>=6.0.2,<6.1.0)
Requires-Dist: openpyxl (>=3.1.2,<3.2.0)
Requires-Dist: pendulum (>=3.1.0,<3.2.0)
Requires-Dist: requests (>=2.32.5,<2.33.0)
Project-URL: Documentation, https://github.com/Big-Dig-Data/celus-pycounter/blob/master/README.rst
